{
	"addedIn": "v6.2.7",
	"build": 1157,
	"http_method": "GET",
	"http_status": 200,
	"mergedVersions": "v6.2.7,v6.4.0,v6.4.2,v6.4.3,v6.4.5,v6.4.6,v6.4.7,v6.4.8,v7.0.0,v7.0.1,v7.0.2,v7.0.3,v7.0.4,v7.2.0",
	"name": "internet-service",
	"path": "firewall",
	"results": {
		"access_group": "fwgrp",
		"category": "table",
		"children": {
			"database": {
				"category": "unitary",
				"default": "isdb",
				"help": "Database name this Internet Service belongs to.",
				"multiple_values": false,
				"name": "database",
				"options": [
					{
						"help": "Internet Service Database.",
						"name": "isdb"
					},
					{
						"help": "Internet RRR Database.",
						"name": "irdb"
					}
				],
				"readonly": true,
				"type": "option"
			},
			"direction": {
				"category": "unitary",
				"default": "both",
				"help": "How this service may be used in a firewall policy (source, destination or both).",
				"multiple_values": false,
				"name": "direction",
				"options": [
					{
						"help": "As source in the firewall policy.",
						"name": "src"
					},
					{
						"help": "As destination in the firewall policy.",
						"name": "dst"
					},
					{
						"help": "Both directions in the firewall policy.",
						"name": "both"
					}
				],
				"readonly": true,
				"type": "option"
			},
			"extra-ip-range-number": {
				"category": "unitary",
				"default": 0,
				"help": "Extra number of IP ranges.",
				"max-value": 4294967295,
				"min-value": 0,
				"multiple_values": false,
				"name": "extra-ip-range-number",
				"readonly": true,
				"type": "integer"
			},
			"icon-id": {
				"category": "unitary",
				"default": 0,
				"help": "Icon ID of Internet Service.",
				"max-value": 4294967295,
				"min-value": 0,
				"multiple_values": false,
				"name": "icon-id",
				"readonly": true,
				"type": "integer"
			},
			"id": {
				"category": "unitary",
				"default": 0,
				"help": "Internet Service ID.",
				"max-value": 4294967295,
				"min-value": 0,
				"multiple_values": false,
				"name": "id",
				"readonly": true,
				"type": "integer"
			},
			"ip-number": {
				"category": "unitary",
				"default": 0,
				"help": "Total number of IP addresses.",
				"max-value": 4294967295,
				"min-value": 0,
				"multiple_values": false,
				"name": "ip-number",
				"readonly": true,
				"type": "integer"
			},
			"ip-range-number": {
				"category": "unitary",
				"default": 0,
				"help": "Number of IP ranges.",
				"max-value": 4294967295,
				"min-value": 0,
				"multiple_values": false,
				"name": "ip-range-number",
				"readonly": true,
				"type": "integer"
			},
			"name": {
				"category": "unitary",
				"default": "",
				"help": "Internet Service name.",
				"multiple_values": false,
				"name": "name",
				"readonly": true,
				"size": 63,
				"type": "string"
			},
			"obsolete": {
				"category": "unitary",
				"default": 0,
				"help": "Indicates whether the Internet Service can be used.",
				"max-value": 255,
				"min-value": 0,
				"multiple_values": false,
				"name": "obsolete",
				"readonly": true,
				"type": "integer"
			},
			"reputation": {
				"category": "unitary",
				"help": "Reputation level of the Internet Service.",
				"max-value": 4294967295,
				"min-value": 0,
				"name": "reputation",
				"readonly": true,
				"removedIn": "v6.4.0",
				"type": "integer"
			},
			"singularity": {
				"category": "unitary",
				"default": 0,
				"help": "Singular level of the Internet Service.",
				"max-value": 65535,
				"min-value": 0,
				"multiple_values": false,
				"name": "singularity",
				"readonly": true,
				"type": "integer"
			},
			"sld-id": {
				"category": "unitary",
				"help": "Second Level Domain.",
				"max-value": 4294967295,
				"min-value": 0,
				"name": "sld-id",
				"readonly": true,
				"removedIn": "v6.4.0",
				"type": "integer"
			}
		},
		"help": "Show Internet Service application.",
		"max_table_size_global": 0,
		"max_table_size_item": 0,
		"max_table_size_vdom": 0,
		"mkey": "id",
		"mkey_type": "integer",
		"name": "internet-service",
		"path": "firewall",
		"q_type": 344,
		"readonly": true
	},
	"revision": "5eb6c6f76b64e67351abf75439a24ee1",
	"serial": "FGTAZRIPD-OKNB34",
	"status": "success",
	"vdom": "root",
	"version": "v7.2.0"
}