{
	"addedIn": "v6.2.7",
	"build": 1157,
	"http_method": "GET",
	"http_status": 200,
	"mergedVersions": "v6.2.7,v6.4.0,v6.4.2,v6.4.3,v6.4.5,v6.4.6,v6.4.7,v6.4.8,v7.0.0,v7.0.1,v7.0.2,v7.0.3,v7.0.4,v7.2.0",
	"name": "profile",
	"path": "voip",
	"results": {
		"access_group": "utmgrp",
		"category": "table",
		"children": {
			"comment": {
				"category": "unitary",
				"help": "Comment.",
				"multiple_values": false,
				"name": "comment",
				"size": 255,
				"type": "var-string"
			},
			"feature-set": {
				"addedIn": "v7.0.0",
				"category": "unitary",
				"default": "proxy",
				"help": "Flow or proxy inspection feature set.",
				"multiple_values": false,
				"name": "feature-set",
				"options": [
					{
						"help": "Flow feature set.",
						"name": "flow"
					},
					{
						"help": "Proxy feature set.",
						"name": "proxy"
					}
				],
				"type": "option"
			},
			"msrp": {
				"addedIn": "v7.0.2",
				"category": "complex",
				"children": {
					"log-violations": {
						"category": "unitary",
						"default": "enable",
						"help": "Enable/disable logging of MSRP violations.",
						"multiple_values": false,
						"name": "log-violations",
						"options": [
							{
								"help": "Disable status.",
								"name": "disable"
							},
							{
								"help": "Enable status.",
								"name": "enable"
							}
						],
						"type": "option"
					},
					"max-msg-size": {
						"category": "unitary",
						"default": 0,
						"help": "Maximum allowable MSRP message size (1-65535).",
						"max-value": 65535,
						"min-value": 0,
						"multiple_values": false,
						"name": "max-msg-size",
						"type": "integer"
					},
					"max-msg-size-action": {
						"category": "unitary",
						"default": "pass",
						"help": "Action for violation of max-msg-size.",
						"multiple_values": false,
						"name": "max-msg-size-action",
						"options": [
							{
								"help": "Pass or allow matching traffic.",
								"name": "pass"
							},
							{
								"help": "Block or drop matching traffic.",
								"name": "block"
							},
							{
								"help": "Reset sessions for matching traffic.",
								"name": "reset"
							},
							{
								"help": "Pass and log matching traffic.",
								"name": "monitor"
							}
						],
						"type": "option"
					},
					"status": {
						"category": "unitary",
						"default": "enable",
						"help": "Enable/disable MSRP.",
						"multiple_values": false,
						"name": "status",
						"options": [
							{
								"help": "Disable status.",
								"name": "disable"
							},
							{
								"help": "Enable status.",
								"name": "enable"
							}
						],
						"type": "option"
					}
				},
				"help": "MSRP.",
				"multiple_values": false,
				"name": "msrp"
			},
			"name": {
				"category": "unitary",
				"default": "",
				"help": "Profile name.",
				"multiple_values": false,
				"name": "name",
				"required": true,
				"size": 35,
				"type": "string"
			},
			"sccp": {
				"category": "complex",
				"children": {
					"block-mcast": {
						"category": "unitary",
						"default": "disable",
						"help": "Enable/disable block multicast RTP connections.",
						"multiple_values": false,
						"name": "block-mcast",
						"options": [
							{
								"help": "Disable status.",
								"name": "disable"
							},
							{
								"help": "Enable status.",
								"name": "enable"
							}
						],
						"type": "option"
					},
					"log-call-summary": {
						"category": "unitary",
						"default": "disable",
						"help": "Enable/disable log summary of SCCP calls.",
						"multiple_values": false,
						"name": "log-call-summary",
						"options": [
							{
								"help": "Disable status.",
								"name": "disable"
							},
							{
								"help": "Enable status.",
								"name": "enable"
							}
						],
						"type": "option"
					},
					"log-violations": {
						"category": "unitary",
						"default": "disable",
						"help": "Enable/disable logging of SCCP violations.",
						"multiple_values": false,
						"name": "log-violations",
						"options": [
							{
								"help": "Disable status.",
								"name": "disable"
							},
							{
								"help": "Enable status.",
								"name": "enable"
							}
						],
						"type": "option"
					},
					"max-calls": {
						"category": "unitary",
						"default": 0,
						"help": "Maximum calls per minute per SCCP client (max 65535).",
						"max-value": 65535,
						"min-value": 0,
						"multiple_values": false,
						"name": "max-calls",
						"type": "integer"
					},
					"status": {
						"category": "unitary",
						"default": "enable",
						"help": "Enable/disable SCCP.",
						"multiple_values": false,
						"name": "status",
						"options": [
							{
								"help": "Disable status.",
								"name": "disable"
							},
							{
								"help": "Enable status.",
								"name": "enable"
							}
						],
						"type": "option"
					},
					"verify-header": {
						"category": "unitary",
						"default": "disable",
						"help": "Enable/disable verify SCCP header content.",
						"multiple_values": false,
						"name": "verify-header",
						"options": [
							{
								"help": "Disable status.",
								"name": "disable"
							},
							{
								"help": "Enable status.",
								"name": "enable"
							}
						],
						"type": "option"
					}
				},
				"help": "SCCP.",
				"multiple_values": false,
				"name": "sccp"
			},
			"sip": {
				"category": "complex",
				"children": {
					"ack-rate": {
						"category": "unitary",
						"default": 0,
						"help": "ACK request rate limit (per second, per policy).",
						"max-value": 4294967295,
						"min-value": 0,
						"multiple_values": false,
						"name": "ack-rate",
						"type": "integer"
					},
					"ack-rate-track": {
						"addedIn": "v7.0.0",
						"category": "unitary",
						"default": "none",
						"help": "Track the packet protocol field.",
						"multiple_values": false,
						"name": "ack-rate-track",
						"options": [
							{
								"help": "None.",
								"name": "none"
							},
							{
								"help": "Source IP.",
								"name": "src-ip"
							},
							{
								"help": "Destination IP.",
								"name": "dest-ip"
							}
						],
						"type": "option"
					},
					"block-ack": {
						"category": "unitary",
						"default": "disable",
						"help": "Enable/disable block ACK requests.",
						"multiple_values": false,
						"name": "block-ack",
						"options": [
							{
								"help": "Disable status.",
								"name": "disable"
							},
							{
								"help": "Enable status.",
								"name": "enable"
							}
						],
						"type": "option"
					},
					"block-bye": {
						"category": "unitary",
						"default": "disable",
						"help": "Enable/disable block BYE requests.",
						"multiple_values": false,
						"name": "block-bye",
						"options": [
							{
								"help": "Disable status.",
								"name": "disable"
							},
							{
								"help": "Enable status.",
								"name": "enable"
							}
						],
						"type": "option"
					},
					"block-cancel": {
						"category": "unitary",
						"default": "disable",
						"help": "Enable/disable block CANCEL requests.",
						"multiple_values": false,
						"name": "block-cancel",
						"options": [
							{
								"help": "Disable status.",
								"name": "disable"
							},
							{
								"help": "Enable status.",
								"name": "enable"
							}
						],
						"type": "option"
					},
					"block-geo-red-options": {
						"category": "unitary",
						"default": "disable",
						"help": "Enable/disable block OPTIONS requests, but OPTIONS requests still notify for redundancy.",
						"multiple_values": false,
						"name": "block-geo-red-options",
						"options": [
							{
								"help": "Disable status.",
								"name": "disable"
							},
							{
								"help": "Enable status.",
								"name": "enable"
							}
						],
						"type": "option"
					},
					"block-info": {
						"category": "unitary",
						"default": "disable",
						"help": "Enable/disable block INFO requests.",
						"multiple_values": false,
						"name": "block-info",
						"options": [
							{
								"help": "Disable status.",
								"name": "disable"
							},
							{
								"help": "Enable status.",
								"name": "enable"
							}
						],
						"type": "option"
					},
					"block-invite": {
						"category": "unitary",
						"default": "disable",
						"help": "Enable/disable block INVITE requests.",
						"multiple_values": false,
						"name": "block-invite",
						"options": [
							{
								"help": "Disable status.",
								"name": "disable"
							},
							{
								"help": "Enable status.",
								"name": "enable"
							}
						],
						"type": "option"
					},
					"block-long-lines": {
						"category": "unitary",
						"default": "enable",
						"help": "Enable/disable block requests with headers exceeding max-line-length.",
						"multiple_values": false,
						"name": "block-long-lines",
						"options": [
							{
								"help": "Disable status.",
								"name": "disable"
							},
							{
								"help": "Enable status.",
								"name": "enable"
							}
						],
						"type": "option"
					},
					"block-message": {
						"category": "unitary",
						"default": "disable",
						"help": "Enable/disable block MESSAGE requests.",
						"multiple_values": false,
						"name": "block-message",
						"options": [
							{
								"help": "Disable status.",
								"name": "disable"
							},
							{
								"help": "Enable status.",
								"name": "enable"
							}
						],
						"type": "option"
					},
					"block-notify": {
						"category": "unitary",
						"default": "disable",
						"help": "Enable/disable block NOTIFY requests.",
						"multiple_values": false,
						"name": "block-notify",
						"options": [
							{
								"help": "Disable status.",
								"name": "disable"
							},
							{
								"help": "Enable status.",
								"name": "enable"
							}
						],
						"type": "option"
					},
					"block-options": {
						"category": "unitary",
						"default": "disable",
						"help": "Enable/disable block OPTIONS requests and no OPTIONS as notifying message for redundancy either.",
						"multiple_values": false,
						"name": "block-options",
						"options": [
							{
								"help": "Disable status.",
								"name": "disable"
							},
							{
								"help": "Enable status.",
								"name": "enable"
							}
						],
						"type": "option"
					},
					"block-prack": {
						"category": "unitary",
						"default": "disable",
						"help": "Enable/disable block prack requests.",
						"multiple_values": false,
						"name": "block-prack",
						"options": [
							{
								"help": "Disable status.",
								"name": "disable"
							},
							{
								"help": "Enable status.",
								"name": "enable"
							}
						],
						"type": "option"
					},
					"block-publish": {
						"category": "unitary",
						"default": "disable",
						"help": "Enable/disable block PUBLISH requests.",
						"multiple_values": false,
						"name": "block-publish",
						"options": [
							{
								"help": "Disable status.",
								"name": "disable"
							},
							{
								"help": "Enable status.",
								"name": "enable"
							}
						],
						"type": "option"
					},
					"block-refer": {
						"category": "unitary",
						"default": "disable",
						"help": "Enable/disable block REFER requests.",
						"multiple_values": false,
						"name": "block-refer",
						"options": [
							{
								"help": "Disable status.",
								"name": "disable"
							},
							{
								"help": "Enable status.",
								"name": "enable"
							}
						],
						"type": "option"
					},
					"block-register": {
						"category": "unitary",
						"default": "disable",
						"help": "Enable/disable block REGISTER requests.",
						"multiple_values": false,
						"name": "block-register",
						"options": [
							{
								"help": "Disable status.",
								"name": "disable"
							},
							{
								"help": "Enable status.",
								"name": "enable"
							}
						],
						"type": "option"
					},
					"block-subscribe": {
						"category": "unitary",
						"default": "disable",
						"help": "Enable/disable block SUBSCRIBE requests.",
						"multiple_values": false,
						"name": "block-subscribe",
						"options": [
							{
								"help": "Disable status.",
								"name": "disable"
							},
							{
								"help": "Enable status.",
								"name": "enable"
							}
						],
						"type": "option"
					},
					"block-unknown": {
						"category": "unitary",
						"default": "enable",
						"help": "Block unrecognized SIP requests (enabled by default).",
						"multiple_values": false,
						"name": "block-unknown",
						"options": [
							{
								"help": "Disable status.",
								"name": "disable"
							},
							{
								"help": "Enable status.",
								"name": "enable"
							}
						],
						"type": "option"
					},
					"block-update": {
						"category": "unitary",
						"default": "disable",
						"help": "Enable/disable block UPDATE requests.",
						"multiple_values": false,
						"name": "block-update",
						"options": [
							{
								"help": "Disable status.",
								"name": "disable"
							},
							{
								"help": "Enable status.",
								"name": "enable"
							}
						],
						"type": "option"
					},
					"bye-rate": {
						"category": "unitary",
						"default": 0,
						"help": "BYE request rate limit (per second, per policy).",
						"max-value": 4294967295,
						"min-value": 0,
						"multiple_values": false,
						"name": "bye-rate",
						"type": "integer"
					},
					"bye-rate-track": {
						"addedIn": "v7.0.0",
						"category": "unitary",
						"default": "none",
						"help": "Track the packet protocol field.",
						"multiple_values": false,
						"name": "bye-rate-track",
						"options": [
							{
								"help": "None.",
								"name": "none"
							},
							{
								"help": "Source IP.",
								"name": "src-ip"
							},
							{
								"help": "Destination IP.",
								"name": "dest-ip"
							}
						],
						"type": "option"
					},
					"call-keepalive": {
						"category": "unitary",
						"default": 0,
						"help": "Continue tracking calls with no RTP for this many minutes.",
						"max-value": 10080,
						"min-value": 0,
						"multiple_values": false,
						"name": "call-keepalive",
						"type": "integer"
					},
					"cancel-rate": {
						"category": "unitary",
						"default": 0,
						"help": "CANCEL request rate limit (per second, per policy).",
						"max-value": 4294967295,
						"min-value": 0,
						"multiple_values": false,
						"name": "cancel-rate",
						"type": "integer"
					},
					"cancel-rate-track": {
						"addedIn": "v7.0.0",
						"category": "unitary",
						"default": "none",
						"help": "Track the packet protocol field.",
						"multiple_values": false,
						"name": "cancel-rate-track",
						"options": [
							{
								"help": "None.",
								"name": "none"
							},
							{
								"help": "Source IP.",
								"name": "src-ip"
							},
							{
								"help": "Destination IP.",
								"name": "dest-ip"
							}
						],
						"type": "option"
					},
					"contact-fixup": {
						"category": "unitary",
						"default": "enable",
						"help": "Fixup contact anyway even if contact's IP:port doesn't match session's IP:port.",
						"multiple_values": false,
						"name": "contact-fixup",
						"options": [
							{
								"help": "Disable status.",
								"name": "disable"
							},
							{
								"help": "Enable status.",
								"name": "enable"
							}
						],
						"type": "option"
					},
					"hnt-restrict-source-ip": {
						"category": "unitary",
						"default": "disable",
						"help": "Enable/disable restrict RTP source IP to be the same as SIP source IP when HNT is enabled.",
						"multiple_values": false,
						"name": "hnt-restrict-source-ip",
						"options": [
							{
								"help": "Disable status.",
								"name": "disable"
							},
							{
								"help": "Enable status.",
								"name": "enable"
							}
						],
						"type": "option"
					},
					"hosted-nat-traversal": {
						"category": "unitary",
						"default": "disable",
						"help": "Hosted NAT Traversal (HNT).",
						"multiple_values": false,
						"name": "hosted-nat-traversal",
						"options": [
							{
								"help": "Disable status.",
								"name": "disable"
							},
							{
								"help": "Enable status.",
								"name": "enable"
							}
						],
						"type": "option"
					},
					"info-rate": {
						"category": "unitary",
						"default": 0,
						"help": "INFO request rate limit (per second, per policy).",
						"max-value": 4294967295,
						"min-value": 0,
						"multiple_values": false,
						"name": "info-rate",
						"type": "integer"
					},
					"info-rate-track": {
						"addedIn": "v7.0.0",
						"category": "unitary",
						"default": "none",
						"help": "Track the packet protocol field.",
						"multiple_values": false,
						"name": "info-rate-track",
						"options": [
							{
								"help": "None.",
								"name": "none"
							},
							{
								"help": "Source IP.",
								"name": "src-ip"
							},
							{
								"help": "Destination IP.",
								"name": "dest-ip"
							}
						],
						"type": "option"
					},
					"invite-rate": {
						"category": "unitary",
						"default": 0,
						"help": "INVITE request rate limit (per second, per policy).",
						"max-value": 4294967295,
						"min-value": 0,
						"multiple_values": false,
						"name": "invite-rate",
						"type": "integer"
					},
					"invite-rate-track": {
						"addedIn": "v7.0.0",
						"category": "unitary",
						"default": "none",
						"help": "Track the packet protocol field.",
						"multiple_values": false,
						"name": "invite-rate-track",
						"options": [
							{
								"help": "None.",
								"name": "none"
							},
							{
								"help": "Source IP.",
								"name": "src-ip"
							},
							{
								"help": "Destination IP.",
								"name": "dest-ip"
							}
						],
						"type": "option"
					},
					"ips-rtp": {
						"category": "unitary",
						"default": "enable",
						"help": "Enable/disable allow IPS on RTP.",
						"multiple_values": false,
						"name": "ips-rtp",
						"options": [
							{
								"help": "Disable status.",
								"name": "disable"
							},
							{
								"help": "Enable status.",
								"name": "enable"
							}
						],
						"type": "option"
					},
					"log-call-summary": {
						"category": "unitary",
						"default": "enable",
						"help": "Enable/disable logging of SIP call summary.",
						"multiple_values": false,
						"name": "log-call-summary",
						"options": [
							{
								"help": "Disable status.",
								"name": "disable"
							},
							{
								"help": "Enable status.",
								"name": "enable"
							}
						],
						"type": "option"
					},
					"log-violations": {
						"category": "unitary",
						"default": "disable",
						"help": "Enable/disable logging of SIP violations.",
						"multiple_values": false,
						"name": "log-violations",
						"options": [
							{
								"help": "Disable status.",
								"name": "disable"
							},
							{
								"help": "Enable status.",
								"name": "enable"
							}
						],
						"type": "option"
					},
					"malformed-header-allow": {
						"category": "unitary",
						"default": "pass",
						"help": "Action for malformed Allow header.",
						"multiple_values": false,
						"name": "malformed-header-allow",
						"options": [
							{
								"help": "Discard malformed messages.",
								"name": "discard"
							},
							{
								"help": "Bypass malformed messages.",
								"name": "pass"
							},
							{
								"help": "Respond with error code.",
								"name": "respond"
							}
						],
						"type": "option"
					},
					"malformed-header-call-id": {
						"category": "unitary",
						"default": "pass",
						"help": "Action for malformed Call-ID header.",
						"multiple_values": false,
						"name": "malformed-header-call-id",
						"options": [
							{
								"help": "Discard malformed messages.",
								"name": "discard"
							},
							{
								"help": "Bypass malformed messages.",
								"name": "pass"
							},
							{
								"help": "Respond with error code.",
								"name": "respond"
							}
						],
						"type": "option"
					},
					"malformed-header-contact": {
						"category": "unitary",
						"default": "pass",
						"help": "Action for malformed Contact header.",
						"multiple_values": false,
						"name": "malformed-header-contact",
						"options": [
							{
								"help": "Discard malformed messages.",
								"name": "discard"
							},
							{
								"help": "Bypass malformed messages.",
								"name": "pass"
							},
							{
								"help": "Respond with error code.",
								"name": "respond"
							}
						],
						"type": "option"
					},
					"malformed-header-content-length": {
						"category": "unitary",
						"default": "pass",
						"help": "Action for malformed Content-Length header.",
						"multiple_values": false,
						"name": "malformed-header-content-length",
						"options": [
							{
								"help": "Discard malformed messages.",
								"name": "discard"
							},
							{
								"help": "Bypass malformed messages.",
								"name": "pass"
							},
							{
								"help": "Respond with error code.",
								"name": "respond"
							}
						],
						"type": "option"
					},
					"malformed-header-content-type": {
						"category": "unitary",
						"default": "pass",
						"help": "Action for malformed Content-Type header.",
						"multiple_values": false,
						"name": "malformed-header-content-type",
						"options": [
							{
								"help": "Discard malformed messages.",
								"name": "discard"
							},
							{
								"help": "Bypass malformed messages.",
								"name": "pass"
							},
							{
								"help": "Respond with error code.",
								"name": "respond"
							}
						],
						"type": "option"
					},
					"malformed-header-cseq": {
						"category": "unitary",
						"default": "pass",
						"help": "Action for malformed CSeq header.",
						"multiple_values": false,
						"name": "malformed-header-cseq",
						"options": [
							{
								"help": "Discard malformed messages.",
								"name": "discard"
							},
							{
								"help": "Bypass malformed messages.",
								"name": "pass"
							},
							{
								"help": "Respond with error code.",
								"name": "respond"
							}
						],
						"type": "option"
					},
					"malformed-header-expires": {
						"category": "unitary",
						"default": "pass",
						"help": "Action for malformed Expires header.",
						"multiple_values": false,
						"name": "malformed-header-expires",
						"options": [
							{
								"help": "Discard malformed messages.",
								"name": "discard"
							},
							{
								"help": "Bypass malformed messages.",
								"name": "pass"
							},
							{
								"help": "Respond with error code.",
								"name": "respond"
							}
						],
						"type": "option"
					},
					"malformed-header-from": {
						"category": "unitary",
						"default": "pass",
						"help": "Action for malformed From header.",
						"multiple_values": false,
						"name": "malformed-header-from",
						"options": [
							{
								"help": "Discard malformed messages.",
								"name": "discard"
							},
							{
								"help": "Bypass malformed messages.",
								"name": "pass"
							},
							{
								"help": "Respond with error code.",
								"name": "respond"
							}
						],
						"type": "option"
					},
					"malformed-header-max-forwards": {
						"category": "unitary",
						"default": "pass",
						"help": "Action for malformed Max-Forwards header.",
						"multiple_values": false,
						"name": "malformed-header-max-forwards",
						"options": [
							{
								"help": "Discard malformed messages.",
								"name": "discard"
							},
							{
								"help": "Bypass malformed messages.",
								"name": "pass"
							},
							{
								"help": "Respond with error code.",
								"name": "respond"
							}
						],
						"type": "option"
					},
					"malformed-header-no-proxy-require": {
						"addedIn": "v7.0.0",
						"category": "unitary",
						"default": "pass",
						"help": "Action for malformed SIP messages without Proxy-Require header.",
						"multiple_values": false,
						"name": "malformed-header-no-proxy-require",
						"options": [
							{
								"help": "Discard malformed messages.",
								"name": "discard"
							},
							{
								"help": "Bypass malformed messages.",
								"name": "pass"
							},
							{
								"help": "Respond with error code.",
								"name": "respond"
							}
						],
						"type": "option"
					},
					"malformed-header-no-require": {
						"addedIn": "v7.0.0",
						"category": "unitary",
						"default": "pass",
						"help": "Action for malformed SIP messages without Require header.",
						"multiple_values": false,
						"name": "malformed-header-no-require",
						"options": [
							{
								"help": "Discard malformed messages.",
								"name": "discard"
							},
							{
								"help": "Bypass malformed messages.",
								"name": "pass"
							},
							{
								"help": "Respond with error code.",
								"name": "respond"
							}
						],
						"type": "option"
					},
					"malformed-header-p-asserted-identity": {
						"category": "unitary",
						"default": "pass",
						"help": "Action for malformed P-Asserted-Identity header.",
						"multiple_values": false,
						"name": "malformed-header-p-asserted-identity",
						"options": [
							{
								"help": "Discard malformed messages.",
								"name": "discard"
							},
							{
								"help": "Bypass malformed messages.",
								"name": "pass"
							},
							{
								"help": "Respond with error code.",
								"name": "respond"
							}
						],
						"type": "option"
					},
					"malformed-header-rack": {
						"category": "unitary",
						"default": "pass",
						"help": "Action for malformed RAck header.",
						"multiple_values": false,
						"name": "malformed-header-rack",
						"options": [
							{
								"help": "Discard malformed messages.",
								"name": "discard"
							},
							{
								"help": "Bypass malformed messages.",
								"name": "pass"
							},
							{
								"help": "Respond with error code.",
								"name": "respond"
							}
						],
						"type": "option"
					},
					"malformed-header-record-route": {
						"category": "unitary",
						"default": "pass",
						"help": "Action for malformed Record-Route header.",
						"multiple_values": false,
						"name": "malformed-header-record-route",
						"options": [
							{
								"help": "Discard malformed messages.",
								"name": "discard"
							},
							{
								"help": "Bypass malformed messages.",
								"name": "pass"
							},
							{
								"help": "Respond with error code.",
								"name": "respond"
							}
						],
						"type": "option"
					},
					"malformed-header-route": {
						"category": "unitary",
						"default": "pass",
						"help": "Action for malformed Route header.",
						"multiple_values": false,
						"name": "malformed-header-route",
						"options": [
							{
								"help": "Discard malformed messages.",
								"name": "discard"
							},
							{
								"help": "Bypass malformed messages.",
								"name": "pass"
							},
							{
								"help": "Respond with error code.",
								"name": "respond"
							}
						],
						"type": "option"
					},
					"malformed-header-rseq": {
						"category": "unitary",
						"default": "pass",
						"help": "Action for malformed RSeq header.",
						"multiple_values": false,
						"name": "malformed-header-rseq",
						"options": [
							{
								"help": "Discard malformed messages.",
								"name": "discard"
							},
							{
								"help": "Bypass malformed messages.",
								"name": "pass"
							},
							{
								"help": "Respond with error code.",
								"name": "respond"
							}
						],
						"type": "option"
					},
					"malformed-header-sdp-a": {
						"category": "unitary",
						"default": "pass",
						"help": "Action for malformed SDP a line.",
						"multiple_values": false,
						"name": "malformed-header-sdp-a",
						"options": [
							{
								"help": "Discard malformed messages.",
								"name": "discard"
							},
							{
								"help": "Bypass malformed messages.",
								"name": "pass"
							},
							{
								"help": "Respond with error code.",
								"name": "respond"
							}
						],
						"type": "option"
					},
					"malformed-header-sdp-b": {
						"category": "unitary",
						"default": "pass",
						"help": "Action for malformed SDP b line.",
						"multiple_values": false,
						"name": "malformed-header-sdp-b",
						"options": [
							{
								"help": "Discard malformed messages.",
								"name": "discard"
							},
							{
								"help": "Bypass malformed messages.",
								"name": "pass"
							},
							{
								"help": "Respond with error code.",
								"name": "respond"
							}
						],
						"type": "option"
					},
					"malformed-header-sdp-c": {
						"category": "unitary",
						"default": "pass",
						"help": "Action for malformed SDP c line.",
						"multiple_values": false,
						"name": "malformed-header-sdp-c",
						"options": [
							{
								"help": "Discard malformed messages.",
								"name": "discard"
							},
							{
								"help": "Bypass malformed messages.",
								"name": "pass"
							},
							{
								"help": "Respond with error code.",
								"name": "respond"
							}
						],
						"type": "option"
					},
					"malformed-header-sdp-i": {
						"category": "unitary",
						"default": "pass",
						"help": "Action for malformed SDP i line.",
						"multiple_values": false,
						"name": "malformed-header-sdp-i",
						"options": [
							{
								"help": "Discard malformed messages.",
								"name": "discard"
							},
							{
								"help": "Bypass malformed messages.",
								"name": "pass"
							},
							{
								"help": "Respond with error code.",
								"name": "respond"
							}
						],
						"type": "option"
					},
					"malformed-header-sdp-k": {
						"category": "unitary",
						"default": "pass",
						"help": "Action for malformed SDP k line.",
						"multiple_values": false,
						"name": "malformed-header-sdp-k",
						"options": [
							{
								"help": "Discard malformed messages.",
								"name": "discard"
							},
							{
								"help": "Bypass malformed messages.",
								"name": "pass"
							},
							{
								"help": "Respond with error code.",
								"name": "respond"
							}
						],
						"type": "option"
					},
					"malformed-header-sdp-m": {
						"category": "unitary",
						"default": "pass",
						"help": "Action for malformed SDP m line.",
						"multiple_values": false,
						"name": "malformed-header-sdp-m",
						"options": [
							{
								"help": "Discard malformed messages.",
								"name": "discard"
							},
							{
								"help": "Bypass malformed messages.",
								"name": "pass"
							},
							{
								"help": "Respond with error code.",
								"name": "respond"
							}
						],
						"type": "option"
					},
					"malformed-header-sdp-o": {
						"category": "unitary",
						"default": "pass",
						"help": "Action for malformed SDP o line.",
						"multiple_values": false,
						"name": "malformed-header-sdp-o",
						"options": [
							{
								"help": "Discard malformed messages.",
								"name": "discard"
							},
							{
								"help": "Bypass malformed messages.",
								"name": "pass"
							},
							{
								"help": "Respond with error code.",
								"name": "respond"
							}
						],
						"type": "option"
					},
					"malformed-header-sdp-r": {
						"category": "unitary",
						"default": "pass",
						"help": "Action for malformed SDP r line.",
						"multiple_values": false,
						"name": "malformed-header-sdp-r",
						"options": [
							{
								"help": "Discard malformed messages.",
								"name": "discard"
							},
							{
								"help": "Bypass malformed messages.",
								"name": "pass"
							},
							{
								"help": "Respond with error code.",
								"name": "respond"
							}
						],
						"type": "option"
					},
					"malformed-header-sdp-s": {
						"category": "unitary",
						"default": "pass",
						"help": "Action for malformed SDP s line.",
						"multiple_values": false,
						"name": "malformed-header-sdp-s",
						"options": [
							{
								"help": "Discard malformed messages.",
								"name": "discard"
							},
							{
								"help": "Bypass malformed messages.",
								"name": "pass"
							},
							{
								"help": "Respond with error code.",
								"name": "respond"
							}
						],
						"type": "option"
					},
					"malformed-header-sdp-t": {
						"category": "unitary",
						"default": "pass",
						"help": "Action for malformed SDP t line.",
						"multiple_values": false,
						"name": "malformed-header-sdp-t",
						"options": [
							{
								"help": "Discard malformed messages.",
								"name": "discard"
							},
							{
								"help": "Bypass malformed messages.",
								"name": "pass"
							},
							{
								"help": "Respond with error code.",
								"name": "respond"
							}
						],
						"type": "option"
					},
					"malformed-header-sdp-v": {
						"category": "unitary",
						"default": "pass",
						"help": "Action for malformed SDP v line.",
						"multiple_values": false,
						"name": "malformed-header-sdp-v",
						"options": [
							{
								"help": "Discard malformed messages.",
								"name": "discard"
							},
							{
								"help": "Bypass malformed messages.",
								"name": "pass"
							},
							{
								"help": "Respond with error code.",
								"name": "respond"
							}
						],
						"type": "option"
					},
					"malformed-header-sdp-z": {
						"category": "unitary",
						"default": "pass",
						"help": "Action for malformed SDP z line.",
						"multiple_values": false,
						"name": "malformed-header-sdp-z",
						"options": [
							{
								"help": "Discard malformed messages.",
								"name": "discard"
							},
							{
								"help": "Bypass malformed messages.",
								"name": "pass"
							},
							{
								"help": "Respond with error code.",
								"name": "respond"
							}
						],
						"type": "option"
					},
					"malformed-header-to": {
						"category": "unitary",
						"default": "pass",
						"help": "Action for malformed To header.",
						"multiple_values": false,
						"name": "malformed-header-to",
						"options": [
							{
								"help": "Discard malformed messages.",
								"name": "discard"
							},
							{
								"help": "Bypass malformed messages.",
								"name": "pass"
							},
							{
								"help": "Respond with error code.",
								"name": "respond"
							}
						],
						"type": "option"
					},
					"malformed-header-via": {
						"category": "unitary",
						"default": "pass",
						"help": "Action for malformed VIA header.",
						"multiple_values": false,
						"name": "malformed-header-via",
						"options": [
							{
								"help": "Discard malformed messages.",
								"name": "discard"
							},
							{
								"help": "Bypass malformed messages.",
								"name": "pass"
							},
							{
								"help": "Respond with error code.",
								"name": "respond"
							}
						],
						"type": "option"
					},
					"malformed-request-line": {
						"category": "unitary",
						"default": "pass",
						"help": "Action for malformed request line.",
						"multiple_values": false,
						"name": "malformed-request-line",
						"options": [
							{
								"help": "Discard malformed messages.",
								"name": "discard"
							},
							{
								"help": "Bypass malformed messages.",
								"name": "pass"
							},
							{
								"help": "Respond with error code.",
								"name": "respond"
							}
						],
						"type": "option"
					},
					"max-body-length": {
						"category": "unitary",
						"default": 0,
						"help": "Maximum SIP message body length (0 meaning no limit).",
						"max-value": 4294967295,
						"min-value": 0,
						"multiple_values": false,
						"name": "max-body-length",
						"type": "integer"
					},
					"max-dialogs": {
						"category": "unitary",
						"default": 0,
						"help": "Maximum number of concurrent calls/dialogs (per policy).",
						"max-value": 4294967295,
						"min-value": 0,
						"multiple_values": false,
						"name": "max-dialogs",
						"type": "integer"
					},
					"max-idle-dialogs": {
						"category": "unitary",
						"default": 0,
						"help": "Maximum number established but idle dialogs to retain (per policy).",
						"max-value": 4294967295,
						"min-value": 0,
						"multiple_values": false,
						"name": "max-idle-dialogs",
						"type": "integer"
					},
					"max-line-length": {
						"category": "unitary",
						"default": 998,
						"help": "Maximum SIP header line length (78-4096).",
						"max-value": 4096,
						"min-value": 78,
						"multiple_values": false,
						"name": "max-line-length",
						"type": "integer"
					},
					"message-rate": {
						"category": "unitary",
						"default": 0,
						"help": "MESSAGE request rate limit (per second, per policy).",
						"max-value": 4294967295,
						"min-value": 0,
						"multiple_values": false,
						"name": "message-rate",
						"type": "integer"
					},
					"message-rate-track": {
						"addedIn": "v7.0.0",
						"category": "unitary",
						"default": "none",
						"help": "Track the packet protocol field.",
						"multiple_values": false,
						"name": "message-rate-track",
						"options": [
							{
								"help": "None.",
								"name": "none"
							},
							{
								"help": "Source IP.",
								"name": "src-ip"
							},
							{
								"help": "Destination IP.",
								"name": "dest-ip"
							}
						],
						"type": "option"
					},
					"nat-port-range": {
						"category": "unitary",
						"default": "5117-65533",
						"help": "RTP NAT port range.",
						"multiple_values": false,
						"name": "nat-port-range",
						"type": "user"
					},
					"nat-trace": {
						"category": "unitary",
						"default": "enable",
						"help": "Enable/disable preservation of original IP in SDP i line.",
						"multiple_values": false,
						"name": "nat-trace",
						"options": [
							{
								"help": "Disable status.",
								"name": "disable"
							},
							{
								"help": "Enable status.",
								"name": "enable"
							}
						],
						"type": "option"
					},
					"no-sdp-fixup": {
						"category": "unitary",
						"default": "disable",
						"help": "Enable/disable no SDP fix-up.",
						"multiple_values": false,
						"name": "no-sdp-fixup",
						"options": [
							{
								"help": "Disable status.",
								"name": "disable"
							},
							{
								"help": "Enable status.",
								"name": "enable"
							}
						],
						"type": "option"
					},
					"notify-rate": {
						"category": "unitary",
						"default": 0,
						"help": "NOTIFY request rate limit (per second, per policy).",
						"max-value": 4294967295,
						"min-value": 0,
						"multiple_values": false,
						"name": "notify-rate",
						"type": "integer"
					},
					"notify-rate-track": {
						"addedIn": "v7.0.0",
						"category": "unitary",
						"default": "none",
						"help": "Track the packet protocol field.",
						"multiple_values": false,
						"name": "notify-rate-track",
						"options": [
							{
								"help": "None.",
								"name": "none"
							},
							{
								"help": "Source IP.",
								"name": "src-ip"
							},
							{
								"help": "Destination IP.",
								"name": "dest-ip"
							}
						],
						"type": "option"
					},
					"open-contact-pinhole": {
						"category": "unitary",
						"default": "enable",
						"help": "Enable/disable open pinhole for non-REGISTER Contact port.",
						"multiple_values": false,
						"name": "open-contact-pinhole",
						"options": [
							{
								"help": "Disable status.",
								"name": "disable"
							},
							{
								"help": "Enable status.",
								"name": "enable"
							}
						],
						"type": "option"
					},
					"open-record-route-pinhole": {
						"category": "unitary",
						"default": "enable",
						"help": "Enable/disable open pinhole for Record-Route port.",
						"multiple_values": false,
						"name": "open-record-route-pinhole",
						"options": [
							{
								"help": "Disable status.",
								"name": "disable"
							},
							{
								"help": "Enable status.",
								"name": "enable"
							}
						],
						"type": "option"
					},
					"open-register-pinhole": {
						"category": "unitary",
						"default": "enable",
						"help": "Enable/disable open pinhole for REGISTER Contact port.",
						"multiple_values": false,
						"name": "open-register-pinhole",
						"options": [
							{
								"help": "Disable status.",
								"name": "disable"
							},
							{
								"help": "Enable status.",
								"name": "enable"
							}
						],
						"type": "option"
					},
					"open-via-pinhole": {
						"category": "unitary",
						"default": "disable",
						"help": "Enable/disable open pinhole for Via port.",
						"multiple_values": false,
						"name": "open-via-pinhole",
						"options": [
							{
								"help": "Disable status.",
								"name": "disable"
							},
							{
								"help": "Enable status.",
								"name": "enable"
							}
						],
						"type": "option"
					},
					"options-rate": {
						"category": "unitary",
						"default": 0,
						"help": "OPTIONS request rate limit (per second, per policy).",
						"max-value": 4294967295,
						"min-value": 0,
						"multiple_values": false,
						"name": "options-rate",
						"type": "integer"
					},
					"options-rate-track": {
						"addedIn": "v7.0.0",
						"category": "unitary",
						"default": "none",
						"help": "Track the packet protocol field.",
						"multiple_values": false,
						"name": "options-rate-track",
						"options": [
							{
								"help": "None.",
								"name": "none"
							},
							{
								"help": "Source IP.",
								"name": "src-ip"
							},
							{
								"help": "Destination IP.",
								"name": "dest-ip"
							}
						],
						"type": "option"
					},
					"prack-rate": {
						"category": "unitary",
						"default": 0,
						"help": "PRACK request rate limit (per second, per policy).",
						"max-value": 4294967295,
						"min-value": 0,
						"multiple_values": false,
						"name": "prack-rate",
						"type": "integer"
					},
					"prack-rate-track": {
						"addedIn": "v7.0.0",
						"category": "unitary",
						"default": "none",
						"help": "Track the packet protocol field.",
						"multiple_values": false,
						"name": "prack-rate-track",
						"options": [
							{
								"help": "None.",
								"name": "none"
							},
							{
								"help": "Source IP.",
								"name": "src-ip"
							},
							{
								"help": "Destination IP.",
								"name": "dest-ip"
							}
						],
						"type": "option"
					},
					"preserve-override": {
						"category": "unitary",
						"default": "disable",
						"help": "Override i line to preserve original IPS (default: append).",
						"multiple_values": false,
						"name": "preserve-override",
						"options": [
							{
								"help": "Disable status.",
								"name": "disable"
							},
							{
								"help": "Enable status.",
								"name": "enable"
							}
						],
						"type": "option"
					},
					"provisional-invite-expiry-time": {
						"category": "unitary",
						"default": 210,
						"help": "Expiry time (10-3600, in seconds) for provisional INVITE.",
						"max-value": 3600,
						"min-value": 10,
						"multiple_values": false,
						"name": "provisional-invite-expiry-time",
						"type": "integer"
					},
					"publish-rate": {
						"category": "unitary",
						"default": 0,
						"help": "PUBLISH request rate limit (per second, per policy).",
						"max-value": 4294967295,
						"min-value": 0,
						"multiple_values": false,
						"name": "publish-rate",
						"type": "integer"
					},
					"publish-rate-track": {
						"addedIn": "v7.0.0",
						"category": "unitary",
						"default": "none",
						"help": "Track the packet protocol field.",
						"multiple_values": false,
						"name": "publish-rate-track",
						"options": [
							{
								"help": "None.",
								"name": "none"
							},
							{
								"help": "Source IP.",
								"name": "src-ip"
							},
							{
								"help": "Destination IP.",
								"name": "dest-ip"
							}
						],
						"type": "option"
					},
					"refer-rate": {
						"category": "unitary",
						"default": 0,
						"help": "REFER request rate limit (per second, per policy).",
						"max-value": 4294967295,
						"min-value": 0,
						"multiple_values": false,
						"name": "refer-rate",
						"type": "integer"
					},
					"refer-rate-track": {
						"addedIn": "v7.0.0",
						"category": "unitary",
						"default": "none",
						"help": "Track the packet protocol field.",
						"multiple_values": false,
						"name": "refer-rate-track",
						"options": [
							{
								"help": "None.",
								"name": "none"
							},
							{
								"help": "Source IP.",
								"name": "src-ip"
							},
							{
								"help": "Destination IP.",
								"name": "dest-ip"
							}
						],
						"type": "option"
					},
					"register-contact-trace": {
						"category": "unitary",
						"default": "disable",
						"help": "Enable/disable trace original IP/port within the contact header of REGISTER requests.",
						"multiple_values": false,
						"name": "register-contact-trace",
						"options": [
							{
								"help": "Disable status.",
								"name": "disable"
							},
							{
								"help": "Enable status.",
								"name": "enable"
							}
						],
						"type": "option"
					},
					"register-rate": {
						"category": "unitary",
						"default": 0,
						"help": "REGISTER request rate limit (per second, per policy).",
						"max-value": 4294967295,
						"min-value": 0,
						"multiple_values": false,
						"name": "register-rate",
						"type": "integer"
					},
					"register-rate-track": {
						"addedIn": "v7.0.0",
						"category": "unitary",
						"default": "none",
						"help": "Track the packet protocol field.",
						"multiple_values": false,
						"name": "register-rate-track",
						"options": [
							{
								"help": "None.",
								"name": "none"
							},
							{
								"help": "Source IP.",
								"name": "src-ip"
							},
							{
								"help": "Destination IP.",
								"name": "dest-ip"
							}
						],
						"type": "option"
					},
					"rfc2543-branch": {
						"category": "unitary",
						"default": "disable",
						"help": "Enable/disable support via branch compliant with RFC 2543.",
						"multiple_values": false,
						"name": "rfc2543-branch",
						"options": [
							{
								"help": "Disable status.",
								"name": "disable"
							},
							{
								"help": "Enable status.",
								"name": "enable"
							}
						],
						"type": "option"
					},
					"rtp": {
						"category": "unitary",
						"default": "enable",
						"help": "Enable/disable create pinholes for RTP traffic to traverse firewall.",
						"multiple_values": false,
						"name": "rtp",
						"options": [
							{
								"help": "Disable status.",
								"name": "disable"
							},
							{
								"help": "Enable status.",
								"name": "enable"
							}
						],
						"type": "option"
					},
					"ssl-algorithm": {
						"category": "unitary",
						"default": "high",
						"help": "Relative strength of encryption algorithms accepted in negotiation.",
						"multiple_values": false,
						"name": "ssl-algorithm",
						"options": [
							{
								"help": "High encryption. Allow only AES and ChaCha.",
								"name": "high"
							},
							{
								"help": "Medium encryption. Allow AES, ChaCha, 3DES, and RC4.",
								"name": "medium"
							},
							{
								"help": "Low encryption. Allow AES, ChaCha, 3DES, RC4, and DES.",
								"name": "low"
							}
						],
						"type": "option"
					},
					"ssl-auth-client": {
						"category": "unitary",
						"datasource": [
							"user.peer.name",
							"user.peergrp.name"
						],
						"default": "",
						"help": "Require a client certificate and authenticate it with the peer/peergrp.",
						"multiple_values": false,
						"name": "ssl-auth-client",
						"size": 35,
						"type": "string"
					},
					"ssl-auth-server": {
						"category": "unitary",
						"datasource": [
							"user.peer.name",
							"user.peergrp.name"
						],
						"default": "",
						"help": "Authenticate the server's certificate with the peer/peergrp.",
						"multiple_values": false,
						"name": "ssl-auth-server",
						"size": 35,
						"type": "string"
					},
					"ssl-client-certificate": {
						"category": "unitary",
						"datasource": [
							"vpn.certificate.local.name"
						],
						"default": "",
						"help": "Name of Certificate to offer to server if requested.",
						"multiple_values": false,
						"name": "ssl-client-certificate",
						"size": 35,
						"type": "string"
					},
					"ssl-client-renegotiation": {
						"category": "unitary",
						"default": "allow",
						"help": "Allow/block client renegotiation by server.",
						"multiple_values": false,
						"name": "ssl-client-renegotiation",
						"options": [
							{
								"help": "Allow a SSL client to renegotiate.",
								"name": "allow"
							},
							{
								"help": "Abort any SSL connection that attempts to renegotiate.",
								"name": "deny"
							},
							{
								"help": "Reject any SSL connection that does not offer a RFC 5746 Secure Renegotiation Indication.",
								"name": "secure"
							}
						],
						"type": "option"
					},
					"ssl-max-version": {
						"category": "unitary",
						"default": "tls-1.3",
						"help": "Highest SSL/TLS version to negotiate.",
						"multiple_values": false,
						"name": "ssl-max-version",
						"options": [
							{
								"help": "SSL 3.0.",
								"name": "ssl-3.0"
							},
							{
								"help": "TLS 1.0.",
								"name": "tls-1.0"
							},
							{
								"help": "TLS 1.1.",
								"name": "tls-1.1"
							},
							{
								"help": "TLS 1.2.",
								"name": "tls-1.2"
							},
							{
								"help": "TLS 1.3.",
								"name": "tls-1.3"
							}
						],
						"type": "option"
					},
					"ssl-min-version": {
						"category": "unitary",
						"default": "tls-1.1",
						"help": "Lowest SSL/TLS version to negotiate.",
						"multiple_values": false,
						"name": "ssl-min-version",
						"options": [
							{
								"help": "SSL 3.0.",
								"name": "ssl-3.0"
							},
							{
								"help": "TLS 1.0.",
								"name": "tls-1.0"
							},
							{
								"help": "TLS 1.1.",
								"name": "tls-1.1"
							},
							{
								"help": "TLS 1.2.",
								"name": "tls-1.2"
							},
							{
								"help": "TLS 1.3.",
								"name": "tls-1.3"
							}
						],
						"type": "option"
					},
					"ssl-mode": {
						"category": "unitary",
						"default": "off",
						"help": "SSL/TLS mode for encryption \u0026 decryption of traffic.",
						"multiple_values": false,
						"name": "ssl-mode",
						"options": [
							{
								"help": "No SSL.",
								"name": "off"
							},
							{
								"help": "Client to FortiGate and FortiGate to Server SSL.",
								"name": "full"
							}
						],
						"type": "option"
					},
					"ssl-pfs": {
						"category": "unitary",
						"default": "allow",
						"help": "SSL Perfect Forward Secrecy.",
						"multiple_values": false,
						"name": "ssl-pfs",
						"options": [
							{
								"help": "PFS mandatory.",
								"name": "require"
							},
							{
								"help": "PFS rejected.",
								"name": "deny"
							},
							{
								"help": "PFS allowed.",
								"name": "allow"
							}
						],
						"type": "option"
					},
					"ssl-send-empty-frags": {
						"category": "unitary",
						"default": "enable",
						"help": "Send empty fragments to avoid attack on CBC IV (SSL 3.0 \u0026 TLS 1.0 only).",
						"multiple_values": false,
						"name": "ssl-send-empty-frags",
						"options": [
							{
								"help": "Send empty fragments.",
								"name": "enable"
							},
							{
								"help": "Do not send empty fragments.",
								"name": "disable"
							}
						],
						"type": "option"
					},
					"ssl-server-certificate": {
						"category": "unitary",
						"datasource": [
							"vpn.certificate.local.name"
						],
						"default": "",
						"help": "Name of Certificate return to the client in every SSL connection.",
						"multiple_values": false,
						"name": "ssl-server-certificate",
						"required": true,
						"size": 35,
						"type": "string"
					},
					"status": {
						"category": "unitary",
						"default": "enable",
						"help": "Enable/disable SIP.",
						"multiple_values": false,
						"name": "status",
						"options": [
							{
								"help": "Disable status.",
								"name": "disable"
							},
							{
								"help": "Enable status.",
								"name": "enable"
							}
						],
						"type": "option"
					},
					"strict-register": {
						"category": "unitary",
						"default": "enable",
						"help": "Enable/disable only allow the registrar to connect.",
						"multiple_values": false,
						"name": "strict-register",
						"options": [
							{
								"help": "Disable status.",
								"name": "disable"
							},
							{
								"help": "Enable status.",
								"name": "enable"
							}
						],
						"type": "option"
					},
					"subscribe-rate": {
						"category": "unitary",
						"default": 0,
						"help": "SUBSCRIBE request rate limit (per second, per policy).",
						"max-value": 4294967295,
						"min-value": 0,
						"multiple_values": false,
						"name": "subscribe-rate",
						"type": "integer"
					},
					"subscribe-rate-track": {
						"addedIn": "v7.0.0",
						"category": "unitary",
						"default": "none",
						"help": "Track the packet protocol field.",
						"multiple_values": false,
						"name": "subscribe-rate-track",
						"options": [
							{
								"help": "None.",
								"name": "none"
							},
							{
								"help": "Source IP.",
								"name": "src-ip"
							},
							{
								"help": "Destination IP.",
								"name": "dest-ip"
							}
						],
						"type": "option"
					},
					"unknown-header": {
						"category": "unitary",
						"default": "pass",
						"help": "Action for unknown SIP header.",
						"multiple_values": false,
						"name": "unknown-header",
						"options": [
							{
								"help": "Discard malformed messages.",
								"name": "discard"
							},
							{
								"help": "Bypass malformed messages.",
								"name": "pass"
							},
							{
								"help": "Respond with error code.",
								"name": "respond"
							}
						],
						"type": "option"
					},
					"update-rate": {
						"category": "unitary",
						"default": 0,
						"help": "UPDATE request rate limit (per second, per policy).",
						"max-value": 4294967295,
						"min-value": 0,
						"multiple_values": false,
						"name": "update-rate",
						"type": "integer"
					},
					"update-rate-track": {
						"addedIn": "v7.0.0",
						"category": "unitary",
						"default": "none",
						"help": "Track the packet protocol field.",
						"multiple_values": false,
						"name": "update-rate-track",
						"options": [
							{
								"help": "None.",
								"name": "none"
							},
							{
								"help": "Source IP.",
								"name": "src-ip"
							},
							{
								"help": "Destination IP.",
								"name": "dest-ip"
							}
						],
						"type": "option"
					}
				},
				"help": "SIP.",
				"multiple_values": false,
				"name": "sip"
			}
		},
		"help": "Configure VoIP profiles.",
		"max_table_size_global": 0,
		"max_table_size_item": 0,
		"max_table_size_vdom": 256,
		"mkey": "name",
		"mkey_type": "string",
		"name": "profile",
		"path": "voip",
		"q_type": 439
	},
	"revision": "f7fe814ab31b35c3001ba0b65166d017",
	"serial": "FGTAZRIPD-OKNB34",
	"status": "success",
	"vdom": "root",
	"version": "v7.2.0"
}